deep_density_estimation/Models.py
deep_density_estimation/Models1.py
deep_density_estimation/PDF_Generation.py
deep_density_estimation/__init__.py
deep_density_estimation/estimate.py
deep_density_estimation/train.py
deep_density_estimation/trainnet.py
deep_density_estimation/utils.py
deep_density_estimation/utils1.py
deep_density_estimation/trained_states/__init__.py
deep_density_estimation/trained_states/10d/10d_128.ckpt.data-00000-of-00001
deep_density_estimation/trained_states/10d/10d_128.ckpt.index
deep_density_estimation/trained_states/10d/__init__.py
deep_density_estimation/trained_states/1d/1d_128.ckpt.data-00000-of-00001
deep_density_estimation/trained_states/1d/1d_128.ckpt.index
deep_density_estimation/trained_states/1d/1d_128.ckpt.meta
deep_density_estimation/trained_states/1d/__init__.py
deep_density_estimation/trained_states/2d/2d_128.ckpt.data-00000-of-00001
deep_density_estimation/trained_states/2d/2d_128.ckpt.index
deep_density_estimation/trained_states/2d/2d_128.ckpt.meta
deep_density_estimation/trained_states/2d/__init__.py
deep_density_estimation/trained_states/30d/30d_128.ckpt.data-00000-of-00001
deep_density_estimation/trained_states/30d/30d_128.ckpt.index
deep_density_estimation/trained_states/30d/__init__.py
deep_density_estimation/trained_states/3d/3d_128.ckpt.data-00000-of-00001
deep_density_estimation/trained_states/3d/3d_128.ckpt.index
deep_density_estimation/trained_states/3d/3d_128.ckpt.meta
deep_density_estimation/trained_states/3d/__init__.py
deep_density_estimation/trained_states/5d/5d_128.ckpt.data-00000-of-00001
deep_density_estimation/trained_states/5d/5d_128.ckpt.index
deep_density_estimation/trained_states/5d/__init__.py
deep_density_estimation-0.1.2.dist-info/METADATA
deep_density_estimation-0.1.2.dist-info/WHEEL
deep_density_estimation-0.1.2.dist-info/top_level.txt
deep_density_estimation-0.1.2.dist-info/RECORD
