Metadata-Version: 2.1
Name: deep-density-estimation
Version: 0.1.2
Summary: data-driven deep density estimation
Home-page: https://github.com/trikpachu/DDE
Author: Patrik Puchert
Author-email: patrik.puchert@uni-ulm.de
License: UNKNOWN
Platform: UNKNOWN
Classifier: Programming Language :: Python :: 3
Classifier: License :: OSI Approved :: MIT License
Classifier: Operating System :: OS Independent
Classifier: Environment :: GPU :: NVIDIA CUDA :: 11.0
Requires-Python: >=3.9
Requires-Dist: numpy (>='1.18.0')
Requires-Dist: pandas (>='1.1.4')
Requires-Dist: Pillow (>='7.0.0')
Requires-Dist: scikit-learn (>='0.23.2')
Requires-Dist: scipy (>='1.5.4')
